diffusion_models/__init__.py
diffusion_models-0.0.0.dist-info/LICENSE
diffusion_models-0.0.0.dist-info/WHEEL
diffusion_models-0.0.0.dist-info/METADATA
diffusion_models-0.0.0.dist-info/RECORD
